{
  "gitSyncId": "68cfb469f9328044162b3f96_e7398dbf-35ce-489d-8549-209240c7642b",
  "id": "AdminPage_autorefresh.stopAutoRefresh",
  "pluginId": "js-plugin",
  "pluginType": "JS",
  "unpublishedAction": {
    "actionConfiguration": {
      "encodeParamsToggle": true,
      "jsArguments": [],
      "paginationType": "NONE",
      "timeoutInMillisecond": 10000
    },
    "collectionId": "AdminPage_autorefresh",
    "confirmBeforeExecute": false,
    "datasource": {
      "isAutoGenerated": false,
      "name": "UNUSED_DATASOURCE",
      "pluginId": "js-plugin"
    },
    "dynamicBindingPathList": [
      {
        "key": "body"
      }
    ],
    "fullyQualifiedName": "autorefresh.stopAutoRefresh",
    "name": "stopAutoRefresh",
    "pageId": "AdminPage",
    "runBehaviour": "MANUAL",
    "userSetOnLoad": true
  }
}