{
  "allowZoom": true,
  "animateLoading": true,
  "borderRadius": "{{appsmith.theme.borderRadius.appBorderRadius}}",
  "bottomRow": 48,
  "boxShadow": "{{appsmith.theme.boxShadow.appBoxShadow}}",
  "defaultMarkers": "[\n  {\n    \"lat\": 40.7128,\n    \"long\": -74.006,\n    \"title\": \"New York\"\n  }\n]",
  "dynamicBindingPathList": [
    {
      "key": "borderRadius"
    },
    {
      "key": "boxShadow"
    }
  ],
  "dynamicTriggerPathList": [
    {
      "key": "onCreateMarker"
    }
  ],
  "enableCreateMarker": true,
  "enableMapTypeControl": false,
  "enablePickLocation": true,
  "enableSearch": true,
  "flexVerticalAlignment": "start",
  "isClickedMarkerCentered": true,
  "isDisabled": false,
  "isLoading": false,
  "isVisible": true,
  "key": "xzl40ohixd",
  "leftColumn": 0,
  "mapCenter": {
    "lat": 8.702578899999999,
    "long": 77.72789809999999,
    "title": "Vasanth Nagar, Tirunelveli, Tamil Nadu 627002, India"
  },
  "minWidth": 450,
  "mobileBottomRow": 43,
  "mobileLeftColumn": 2,
  "mobileRightColumn": 26,
  "mobileTopRow": 3,
  "needsErrorInfo": false,
  "onCreateMarker": "{{mapinfo.run()}}",
  "parentColumnSpace": 6.53125,
  "parentId": "6ul23ub6h6",
  "parentRowSpace": 10,
  "renderMode": "CANVAS",
  "responsiveBehavior": "fill",
  "rightColumn": 63,
  "topRow": 8,
  "type": "MAP_WIDGET",
  "version": 1,
  "widgetId": "1dn1rqcumb",
  "widgetName": "Map1",
  "zoomLevel": 50
}